fds/__init__.py
fds/sdk/__init__.py
fds/sdk/IssueTracker/__init__.py
fds/sdk/IssueTracker/api_client.py
fds/sdk/IssueTracker/configuration.py
fds/sdk/IssueTracker/exceptions.py
fds/sdk/IssueTracker/model_utils.py
fds/sdk/IssueTracker/rest.py
fds/sdk/IssueTracker/api/__init__.py
fds/sdk/IssueTracker/api/attachment_api.py
fds/sdk/IssueTracker/api/issue_api.py
fds/sdk/IssueTracker/apis/__init__.py
fds/sdk/IssueTracker/model/__init__.py
fds/sdk/IssueTracker/model/attachment.py
fds/sdk/IssueTracker/model/attachment_response.py
fds/sdk/IssueTracker/model/comment.py
fds/sdk/IssueTracker/model/comment_request.py
fds/sdk/IssueTracker/model/comment_request_data.py
fds/sdk/IssueTracker/model/error.py
fds/sdk/IssueTracker/model/error_response.py
fds/sdk/IssueTracker/model/file_extension.py
fds/sdk/IssueTracker/model/id_response.py
fds/sdk/IssueTracker/model/id_response_data.py
fds/sdk/IssueTracker/model/issue.py
fds/sdk/IssueTracker/model/issue_data.py
fds/sdk/IssueTracker/model/issue_request.py
fds/sdk/IssueTracker/model/issue_request_data.py
fds/sdk/IssueTracker/model/update_issue_request.py
fds/sdk/IssueTracker/model/update_issue_request_data.py
fds/sdk/IssueTracker/models/__init__.py
fds_sdk_issuetracker-0.5.1.dist-info/licenses/LICENSE
fds_sdk_issuetracker-0.5.1.dist-info/METADATA
fds_sdk_issuetracker-0.5.1.dist-info/WHEEL
fds_sdk_issuetracker-0.5.1.dist-info/top_level.txt
fds_sdk_issuetracker-0.5.1.dist-info/RECORD
